dupload/__init__.py
dupload-0.0.4.2.dist-info/LICENSE
dupload-0.0.4.2.dist-info/METADATA
dupload-0.0.4.2.dist-info/WHEEL
dupload-0.0.4.2.dist-info/top_level.txt
dupload-0.0.4.2.dist-info/RECORD
