Metadata-Version: 2.1
Name: dupload
Version: 0.0.4.2
Summary: Upload anywhere, at any time.
Home-page: https://github.com/dwiftejb/dupload
Author: DwifteJB
Author-email: dwifte@icloud.com
License: UNKNOWN
Platform: UNKNOWN
Classifier: Programming Language :: Python :: 3
Classifier: Programming Language :: Python :: 3.4
Classifier: Programming Language :: Python :: 3.8
Requires-Dist: requests
Requires-Dist: bs4
